Workbook

Sheet Дашборд
A1: ЮНИТ-ЭКОНОМИКА ПРОДУКТА
A3: Стоимость ресурсов | E3: Доходность и прибыль
A4: Сумма клиента во Вкладе | B4: =Параметры!B5 -> 500000 | C4: руб. | E4: Привлеченные ресурсы | F4: =Параметры!B22 -> 500000 | G4: руб.
A5: Проценты клиенту за 185 дней | B5: =Параметры!B24 -> 36113.014 | C5: руб. | E5: Средняя сумма кредита | F5: =Параметры!B23 -> 500000 | G5: руб.
A6: Комиссия от второй компании | B6: =Параметры!B21 -> 12500 | C6: руб. | E6: Процентный доход по кредиту за 6 мес. | F6: =Параметры!I11 -> 45476.011 | G6: руб.
A7: Чистая стоимость ресурсов | B7: =B5-B6 -> 23613.014 | C7: руб. | D7: Проценты клиенту минус комиссия | E7: Все расходы за срок | F7: =Расходы!F23 -> 25000 | G7: руб.
A8: Стоимость ресурсов за период / Вклад | B8: =B7/B4 -> 0.047226027 | C8: % | E8: Прибыль до налога | F8: =F6+B6-B5-F7 -> -3137.0024 | G8: руб.
A9: Годовая стоимость ресурсов / Вклад (простая) | B9: =B8*Параметры!B9/Параметры!B6 -> 0.093175676 | C9: % | E9: Налог на прибыль | F9: =MAX(0,F8*Параметры!B15) -> 0 | G9: руб.
A10: Годовая стоимость ресурсов / Вклад (сложная) | B10: =(1+B8)^(Параметры!B9/Параметры!B6)-1 -> 0.09531547 | C10: % | E10: Чистая прибыль на клиента (БЕЗ УЧЁТА КРЕДИТНОГО РИСКА) | F10: =F8-F9 -> -3137.0024 | G10: руб.
A11: Годовая стоимость / доступная сумма | B11: =B7/Параметры!B22*Параметры!B9/Параметры!B6 -> 0.093175676 | C11: % | D11: Учитывает, какая доля X реально работает | E11: Маржа к Вкладу | F11: =F10/B4 -> -0.0062740049 | G11: %
E12: Спред к стоимости ресурсов | F12: =Параметры!B13-B11 -> 0.095524324 | G12: п.п. | H12: Доходность кредитов минус стоимость ресурсов на доступную сумму
E13: Средний срок размещения кредита | F13: =Параметры!B17 -> 48 | G13: мес. | H13: Используется в аннуитетном расчёте процентного дохода через ПЛТ
A15: Компоненты прибыли на одну сделку (БЕЗ УЧЁТА КРЕДИТНОГО РИСКА)
A16: Компонент | B16: Сумма, руб.
A17: Процентный доход по кредитам | B17: =F6 -> 45476.011
A18: Комиссия от второй компании | B18: =B6 -> 12500
A19: Проценты клиенту | B19: =-B5 -> -36113.014
A20: Расходы | B20: =-F7 -> -25000
A21: Налоги | B21: =-F9 -> 0
A22: Чистая прибыль | B22: =F10 -> -3137.0024
A30: СЦЕНАРИИ ПРОДУКТА
A31: Синие значения — изменяемые предположения. В текущем сценарии зелёные значения связаны с основными параметрами модели.
A33: Сценарий | B33: Доля размещения вклада | C33: Доходность кредита | D33: Загрузка | E33: Средний срок кредита, мес. | F33: Стоимость риска | G33: Возможные доп.расходы | H33: Фикс. расходы, руб. | I33: Ставка клиенту | J33: Тип ставки | K33: Доход по кредиту за 6 месяцев, руб. | L33: Вознаграждение Банку руб. | M33: Проценты клиенту, руб. | N33: Кредитные потери, руб. | O33: Прочие расходы (ИТ, менеджеры по продажам и др.), руб. | P33: Прибыль до налога, руб. | Q33: Чистая прибыль, руб. | R33: Маржа к сумме Вклада
A34: Текущая модель | B34: =Параметры!B14 -> 1 | C34: =Параметры!B13 -> 0.1887 | D34: =Параметры!B14 -> 1 | E34: =Параметры!B17 -> 48 | F34: 0 | G34: 0 | H34: =Расходы!F23 -> 25000 | I34: =Параметры!B7 -> 0.1425 | J34: =Параметры!B8 -> Годовая | K34: =-CUMIPMT(C34/12,E34,$B$4,1,6,0) -> 45476.011 | L34: =Параметры!$B$5*Параметры!$B$10*Параметры!$B$11 -> 12500 | M34: =IF(J34="Годовая",Параметры!$B$5*I34*Параметры!$B$6/Параметры!$B$9,Параметры!$B$5*I34) -> 36113.014 | N34: =(Параметры!$B$5*B34*D34*F34)/6 -> 0 | O34: =Параметры!$B$5*G34*Параметры!$B$6/Параметры!$B$9+H34 -> 25000 | P34: =K34+L34-M34-N34-O34 -> -3137.0024 | Q34: =P34-MAX(0,P34*Параметры!$B$15) -> -3137.0024 | R34: =Q34/Параметры!$B$5 -> -0.0062740049
A35: Базовый сценарий (при минимальных расходах на ИТ) | B35: 1 | C35: 0.1887 | D35: 1 | E35: 48 | F35: 0 | G35: 0 | H35: 21500 | I35: 0.1425 | J35: Годовая | K35: =-CUMIPMT(C35/12,E35,$B$4,1,6,0) -> 45476.011 | L35: =Параметры!$B$5*Параметры!$B$10*Параметры!$B$11 -> 12500 | M35: =IF(J35="Годовая",Параметры!$B$5*I35*Параметры!$B$6/Параметры!$B$9,Параметры!$B$5*I35) -> 36113.014 | N35: =(Параметры!$B$5*B35*D35*F35)/6 -> 0 | O35: =Параметры!$B$5*G35*Параметры!$B$6/Параметры!$B$9+H35 -> 21500 | P35: =K35+L35-M35-N35-O35 -> 362.99755 | Q35: =P35-MAX(0,P35*Параметры!$B$15) -> 362.99755 | R35: =Q35/Параметры!$B$5 -> 0.0007259951
A38: Расчёт точки безубыточности
A39: Задача и методика | B39: Есть функция прибыли, зависящая от кредитной ставки. При низкой ставке прибыль отрицательная, при более высокой положительная. Требуется найти такое значение ставки, при котором прибыль становится равной нулю. Эта ставка и является безубыточной. Метод ОПГ / GRG Nonlinear использует приближённые производные функции и последовательно движется к точке, удовлетворяющей заданным ограничениям. Все расходы за исключением "Кредитные потери" исходят из таблицы СЦЕНАРИИ ПРОДУКТА. Данные --> Поиск решения
A40: Возможность изменения | B40: Возможно только с использованием надстройки "Поиск решения" во вкладке Данные | K40: Точка безубыточности по ставке | P40: Точка безубыточности по сумме расходов
A41: Сценарий | B41: Количество клиентов за 6 мес. | C41: =O33 -> Прочие расходы (ИТ, менеджеры по продажам и др.), руб. | D41: Организационные и ИТ Расходы на 1 клиента | E41: =M33 -> Проценты клиенту, руб. | F41: =L33 -> Вознаграждение Банку руб. | G41: =N33 -> Кредитные потери, руб. | H41: =K33 -> Доход по кредиту за 6 месяцев, руб. | I41: Срок кредита | J41: Чистая прибыль, руб. | K41: Ставка безубыточности для данного сценария | L41: =H41 -> Доход по кредиту за 6 месяцев, руб. | M41: Ставка по кредиту | N41: Проценты клиенту | O41: Чистая прибыль, руб. | P41: Безубыточные расходы на ИТ на 1 клиента при фиксированой ставке
A42: Сценарий 1 | B42: 20 | C42: 1000000 | D42: =C42/B42 -> 50000 | E42: =$M$34 -> 36113.014 | F42: =$L$34 -> 12500 | G42: =$N$34 -> 0 | H42: =-CUMIPMT($K$42/12,$I$42,$B$4,1,6,0) -> 73613.014 | I42: =$E$34 -> 48 | J42: =H42+F42-E42-G42-D42 -> -3.339228e-07 | K42: 0.3030163 | L42: =-CUMIPMT(M42/12,I42,$B$4,1,6,0) -> 45476.011 | M42: =$C$34 -> 0.1887 | N42: 30000 | O42: =L42+F42-N42-G42-P42 -> 0 | P42: 27976.011
A43: Сценарий 2 | B43: 20 | C43: 500000 | D43: =C43/B43 -> 25000 | E43: =$M$34 -> 36113.014 | F43: =$L$34 -> 12500 | G43: =$N$34 -> 0 | H43: =-CUMIPMT(K43/12,$I$43,$B$4,1,6,0) -> 48613.014 | I43: =$E$34 -> 48 | J43: =H43+F43-E43-G43-D43 -> 3.1148375e-08 | K43: 0.20151993 | L43: =-CUMIPMT(M43/12,I43,$B$4,1,6,0) -> 38472.358 | M43: 0.16 | N43: 25000 | O43: =L43+F43-N43-G43-P43 -> 0 | P43: 25972.358
A44: Сценарий 3 | B44: 20 | C44: 250000 | D44: =C44/B44 -> 12500 | E44: =$M$34 -> 36113.014 | F44: =$L$34 -> 12500 | G44: =$N$34 -> 0 | H44: =-CUMIPMT(K44/12,$I$44,$B$4,1,6,0) -> 36113.014 | I44: =$E$34 -> 48 | J44: =H44+F44-E44-G44-D44 -> -5.7116267e-09 | K44: 0.15030612 | L44: =-CUMIPMT(M44/12,I44,$B$4,1,6,0) -> 33608.265 | M44: 0.14 | N44: 20000 | O44: =L44+F44-N44-G44-P44 -> 0 | P44: 26108.265

Sheet Параметры
A1: ПАРАМЕТРЫ ЮНИТ-ЭКОНОМИКИ
A3: 1. Базовые условия сделки | H3: Кредитный календарь
A4: Параметр | B4: Значение | C4: Ед. | D4: Сущность | H4: Период | I4: Процентный доход по кредиту
A5: Сумма вклада | B5: 500000 | C5: руб. | D5: Масштаб всей сделки | H5: 1 | I5: =IPMT($B$13/12,H5,$B$17,-$B$23) -> 7862.5
A6: Срок | B6: 185 | C6: дней | D6: Срок начисления процентов | H6: 2 | I6: =IPMT($B$13/12,H6,$B$17,-$B$23) -> 7751.5872
A7: Ставка клиенту | B7: 0.1425 | C7: % | D7: Стоимость привлечённых ресурсов | H7: 3 | I7: =IPMT($B$13/12,H7,$B$17,-$B$23) -> 7638.9302
A8: Тип ставки клиенту | B8: Годовая | D8: Определяет пересчёт 14,25% на 185 дней | H8: 4 | I8: =IPMT($B$13/12,H8,$B$17,-$B$23) -> 7524.5017
A9: Дневная база | B9: 365 | C9: дней | D9: 365 или 360 дней | H9: 5 | I9: =IPMT($B$13/12,H9,$B$17,-$B$23) -> 7408.2739
A10: Условие доли размещения средств в ПДС от суммы вклада | B10: 0.25 | C10: % | D10: База партнёрской операции | H10: 6 | I10: =IPMT($B$13/12,H10,$B$17,-$B$23) -> 7290.2183
A11: Вознаграждение Банку | B11: 0.1 | C11: % | D11: Комиссионный доход | H11: Проценты за 6 мес. | I11: =SUM(I5:I10) -> 45476.011
A12: Коэффициент фактического вклада | B12: 1 | C12: % | D12: Доступная сумма для кредитования
A13: Ставка по кредиту | B13: 0.1887 | C13: % | D13: Процентный доход по кредитам
A14: Доля размещения в кредитные продукты от привлеченного ресурса | B14: 1 | C14: % | D14: Средний работающий кредитный портфель
A15: Налог на прибыль | B15: 0 | C15: % | D15: Чистая прибыль
A16: Возрат суммы вклада клиента по окончанию 185 дней | B16: 1 | C16: % | D16: Контроль ликвидности
A17: Средний срок размещения кредита | B17: 48 | C17: мес. | D17: Среднее число месяцев погашения кредита; допускается дробное значение для среднего срока
A18: 2. Расчёт структуры сделки и контроль ликвидности
A19: Показатель | B19: Формула / значение | C19: Ед.
A20: Сумма клиента в НПФ | B20: =B5*B10 -> 125000 | C20: руб.
A21: Комиссионное вознаграждение | B21: =B20*B11 -> 12500 | C21: руб.
A22: Доступная сумма для кредитования | B22: =B5*B12 -> 500000 | C22: руб.
A23: Средний работающий кредитный портфель | B23: =B22*B14 -> 500000 | C23: руб.
A24: Проценты клиенту за срок | B24: =IF(B8="Годовая",B5*B7*B6/B9,B5*B7) -> 36113.014 | C24: руб.
A25: Процентный доход по кредиту | B25: =(IF(B17=0,0,-PMT(B13/12,B17,B23)*B17-B23)) -> 215957.49 | C25: руб.
A26: Основной долг к возврату клиенту | B26: =B5*B16 -> 500000 | C26: руб.
A27: Разрыв основного долга до доходов | B27: =MAX(0,B26-B22) -> 0 | C27: руб.
A28: Разрыв после комиссии и процентного дохода | B28: =MAX(0,B26+B24-B22-B25-B21) -> 0 | C28: руб.

Sheet Расходы
A1: РАСХОДЫ НА ОДНОГО КЛИЕНТА / ОДНУ СДЕЛКУ
A3: Ставка расхода может быть годовой или за весь срок. Все жёлтые/синие ячейки можно менять.
K4: Количество клиентов | L4: Средняя стоимость
A5: Статья расходов | B5: База расчёта | C5: Ставка | D5: Тип ставки | E5: Фиксированно, руб. | F5: Расход за срок, руб. | G5: Комментарий | I5: IT | J5: 1000000 | K5: 100 | L5: =J5/K5 -> 10000
A6: Привлечение клиента (CAC) | B6: Фиксировано | C6: 0 | D6: За период | E6: 1000 | F6: =IF(B6="Сумма X",Параметры!$B$5,IF(B6="Доступная сумма",Параметры!$B$22,IF(B6="Средний портфель",Параметры!$B$23,IF(B6="Процентный доход",Параметры!$B$25,0))))*C6*IF(D6="Годовая",Параметры!$B$6/Параметры!$B$9,1)+E6 -> 1000 | G6: Реклама, агент, бонус за привлечение | I6: IT | J6: 500000 | K6: 20 | L6: =J6/K6 -> 25000
A7: KYC / AML / идентификация | B7: Фиксировано | C7: 0 | D7: За период | E7: 0 | F7: =IF(B7="Сумма X",Параметры!$B$5,IF(B7="Доступная сумма",Параметры!$B$22,IF(B7="Средний портфель",Параметры!$B$23,IF(B7="Процентный доход",Параметры!$B$25,0))))*C7*IF(D7="Годовая",Параметры!$B$6/Параметры!$B$9,1)+E7 -> 0 | G7: Проверка клиента и документов
A8: Эквайринг и банковские переводы | B8: Фиксировано | C8: 0 | D8: За период | E8: 0 | F8: =IF(B8="Сумма X",Параметры!$B$5,IF(B8="Доступная сумма",Параметры!$B$22,IF(B8="Средний портфель",Параметры!$B$23,IF(B8="Процентный доход",Параметры!$B$25,0))))*C8*IF(D8="Годовая",Параметры!$B$6/Параметры!$B$9,1)+E8 -> 0 | G8: Комиссии банков и платёжных систем
A9: Оформление договора / ЭДО | B9: Фиксировано | C9: 0 | D9: За период | E9: 0 | F9: =IF(B9="Сумма X",Параметры!$B$5,IF(B9="Доступная сумма",Параметры!$B$22,IF(B9="Средний портфель",Параметры!$B$23,IF(B9="Процентный доход",Параметры!$B$25,0))))*C9*IF(D9="Годовая",Параметры!$B$6/Параметры!$B$9,1)+E9 -> 0 | G9: Подпись, SMS, ЭДО, хранение документов
A10: Сопровождение клиента ПДС | B10: Фиксировано | C10: 0 | D10: За период | E10: 0 | F10: =IF(B10="Сумма X",Параметры!$B$5,IF(B10="Доступная сумма",Параметры!$B$22,IF(B10="Средний портфель",Параметры!$B$23,IF(B10="Процентный доход",Параметры!$B$25,0))))*C10*IF(D10="Годовая",Параметры!$B$6/Параметры!$B$9,1)+E10 -> 0 | G10: Поддержка и операционные действия
A11: Скоринг и выдача кредитов | B11: Фиксировано | D11: За период | E11: 0 | F11: =IF(B11="Сумма X",Параметры!$B$5,IF(B11="Доступная сумма",Параметры!$B$22,IF(B11="Средний портфель",Параметры!$B$23,IF(B11="Процентный доход",Параметры!$B$25,0))))*C11*IF(D11="Годовая",Параметры!$B$6/Параметры!$B$9,1)+E11 -> 0 | G11: Бюро кредитных историй, скоринг, оформление
A12: Ожидаемые кредитные потери | B12: Фиксировано | C12: 0 | D12: Годовая | E12: 0 | F12: =IF(B12="Сумма X",Параметры!$B$5,IF(B12="Доступная сумма",Параметры!$B$22,IF(B12="Средний портфель",Параметры!$B$23,IF(B12="Процентный доход",Параметры!$B$25,0))))*C12*IF(D12="Годовая",Параметры!$B$6/Параметры!$B$9,1)+E12 -> 0 | G12: PD × LGD или фактическая стоимость риска
A13: Просрочка и взыскание | B13: Фиксировано | C13: 0 | D13: За период | E13: 0 | F13: =IF(B13="Сумма X",Параметры!$B$5,IF(B13="Доступная сумма",Параметры!$B$22,IF(B13="Средний портфель",Параметры!$B$23,IF(B13="Процентный доход",Параметры!$B$25,0))))*C13*IF(D13="Годовая",Параметры!$B$6/Параметры!$B$9,1)+E13 -> 0 | G13: Коллекторы, суды, взыскание
A14: Страхование / гарантии | B14: Фиксировано | C14: 0 | D14: Годовая | E14: 0 | F14: =IF(B14="Сумма X",Параметры!$B$5,IF(B14="Доступная сумма",Параметры!$B$22,IF(B14="Средний портфель",Параметры!$B$23,IF(B14="Процентный доход",Параметры!$B$25,0))))*C14*IF(D14="Годовая",Параметры!$B$6/Параметры!$B$9,1)+E14 -> 0 | G14: Страховая премия или гарантийная комиссия
A15: Резерв ликвидности | B15: Фиксировано | C15: 0 | D15: Годовая | E15: 0 | F15: =IF(B15="Сумма X",Параметры!$B$5,IF(B15="Доступная сумма",Параметры!$B$22,IF(B15="Средний портфель",Параметры!$B$23,IF(B15="Процентный доход",Параметры!$B$25,0))))*C15*IF(D15="Годовая",Параметры!$B$6/Параметры!$B$9,1)+E15 -> 0 | G15: Стоимость неработающего резерва / фондирования
A16: IT и инфраструктура | B16: Фиксировано | C16: 0 | D16: За период | E16: 0 | F16: 24000 | G16: Серверы, лицензии, интеграции
A17: Персонал на одну сделку | B17: Фиксировано | C17: 0 | D17: За период | E17: 0 | F17: =IF(B17="Сумма X",Параметры!$B$5,IF(B17="Доступная сумма",Параметры!$B$22,IF(B17="Средний портфель",Параметры!$B$23,IF(B17="Процентный доход",Параметры!$B$25,0))))*C17*IF(D17="Годовая",Параметры!$B$6/Параметры!$B$9,1)+E17 -> 0 | G17: Распределённая зарплата и страховые взносы
A18: Юристы, комплаенс, аудит | B18: Фиксировано | C18: 0 | D18: За период | E18: 0 | F18: =IF(B18="Сумма X",Параметры!$B$5,IF(B18="Доступная сумма",Параметры!$B$22,IF(B18="Средний портфель",Параметры!$B$23,IF(B18="Процентный доход",Параметры!$B$25,0))))*C18*IF(D18="Годовая",Параметры!$B$6/Параметры!$B$9,1)+E18 -> 0 | G18: Регуляторная и юридическая нагрузка
A19: Партнёрские / агентские выплаты | B19: Фиксировано | C19: 0 | D19: За период | E19: 0 | F19: =IF(B19="Сумма X",Параметры!$B$5,IF(B19="Доступная сумма",Параметры!$B$22,IF(B19="Средний портфель",Параметры!$B$23,IF(B19="Процентный доход",Параметры!$B$25,0))))*C19*IF(D19="Годовая",Параметры!$B$6/Параметры!$B$9,1)+E19 -> 0 | G19: Иные комиссии посредникам
A20: Налоги и сборы, кроме налога на прибыль | B20: Фиксировано | C20: 0 | D20: За период | E20: 0 | F20: =IF(B20="Сумма X",Параметры!$B$5,IF(B20="Доступная сумма",Параметры!$B$22,IF(B20="Средний портфель",Параметры!$B$23,IF(B20="Процентный доход",Параметры!$B$25,0))))*C20*IF(D20="Годовая",Параметры!$B$6/Параметры!$B$9,1)+E20 -> 0 | G20: Введите только применимые налоги/сборы
A21: Прочие переменные расходы | B21: Фиксировано | C21: 0 | D21: За период | E21: 0 | F21: =IF(B21="Сумма X",Параметры!$B$5,IF(B21="Доступная сумма",Параметры!$B$22,IF(B21="Средний портфель",Параметры!$B$23,IF(B21="Процентный доход",Параметры!$B$25,0))))*C21*IF(D21="Годовая",Параметры!$B$6/Параметры!$B$9,1)+E21 -> 0 | G21: Резерв на неучтённые расходы
A23: ИТОГО РАСХОДОВ | F23: =SUM(F6:F21) -> 25000

Sheet Сценарии
A1: СЦЕНАРНЫЙ АНАЛИЗ
A3: Сценарии — упрощённый быстрый расчёт. Жёлтые/синие предположения можно менять; комиссии Y и срок берутся из листа «Параметры».
A5: Сценарий | B5: Доля размещения Вклада | C5: Доходность кредита | D5: Загрузка | E5: Стоимость риска | F5: Прочие расходы от X | G5: Фикс. расходы | H5: Ставка клиенту | I5: Тип ставки | J5: Доход по кредитам | K5: Комиссия | L5: Проценты клиенту | M5: Кредитные потери | N5: Прочие расходы | O5: Прибыль до налога | P5: Чистая прибыль | Q5: Маржа к X | R5: Безубыт. доходность | S5: Средний срок кредита, мес.
A6: Текущая модель | B6: =Параметры!B12 -> 1 | C6: =Параметры!B13 -> 0.1887 | D6: =Параметры!B14 -> 1 | E6: 0.04 | F6: 0 | G6: =Расходы!F23 -> 25000 | H6: =Параметры!B7 -> 0.1425 | I6: =Параметры!B8 -> Годовая | J6: =IF(S6=0,0,-PMT(C6/12,S6,Параметры!$B$5*B6*D6)*S6-Параметры!$B$5*B6*D6) -> 215957.49 | K6: =Параметры!$B$5*Параметры!$B$10*Параметры!$B$11 -> 12500 | L6: =IF(I6="Годовая",Параметры!$B$5*H6*Параметры!$B$6/Параметры!$B$9,Параметры!$B$5*H6) -> 36113.014 | M6: =Параметры!$B$5*B6*D6*E6*S6/12 -> 80000 | N6: =Параметры!$B$5*F6*Параметры!$B$6/Параметры!$B$9+G6 -> 25000 | O6: =J6+K6-L6-M6-N6 -> 87344.478 | P6: =O6-MAX(0,O6*Параметры!$B$15) -> 87344.478 | Q6: =P6/Параметры!$B$5 -> 0.17468896 | R6: =IF(OR(S6=0,Параметры!$B$5*B6*D6=0),0,12*RATE(S6,-(Параметры!$B$5*B6*D6+L6+M6+N6-K6)/S6,Параметры!$B$5*B6*D6,0)) -> 0.11711095 | S6: =Параметры!B17 -> 48
A7: Консервативный пример | B7: 0.75 | C7: 0.2 | D7: 0.75 | E7: 0.06 | F7: 0.03 | G7: 5000 | H7: 0.1425 | I7: Годовая | J7: =IF(S7=0,0,-PMT(C7/12,S7,Параметры!$B$5*B7*D7)*S7-Параметры!$B$5*B7*D7) -> 11684.359 | K7: =Параметры!$B$5*Параметры!$B$10*Параметры!$B$11 -> 12500 | L7: =IF(I7="Годовая",Параметры!$B$5*H7*Параметры!$B$6/Параметры!$B$9,Параметры!$B$5*H7) -> 36113.014 | M7: =Параметры!$B$5*B7*D7*E7*S7/12 -> 5547.9452 | N7: =Параметры!$B$5*F7*Параметры!$B$6/Параметры!$B$9+G7 -> 12602.74 | O7: =J7+K7-L7-M7-N7 -> -30079.34 | P7: =O7-MAX(0,O7*Параметры!$B$15) -> -30079.34 | Q7: =P7/Параметры!$B$5 -> -0.06015868 | R7: =IF(OR(S7=0,Параметры!$B$5*B7*D7=0),0,12*RATE(S7,-(Параметры!$B$5*B7*D7+L7+M7+N7-K7)/S7,Параметры!$B$5*B7*D7,0)) -> 0.70113872 | S7: 3.9452055
A8: Базовый пример | B8: 1 | C8: 0.28 | D8: 0.9 | E8: 0.03 | F8: 0.015 | G8: 3000 | H8: 0.1425 | I8: Годовая | J8: =IF(S8=0,0,-PMT(C8/12,S8,Параметры!$B$5*B8*D8)*S8-Параметры!$B$5*B8*D8) -> 31610.947 | K8: =Параметры!$B$5*Параметры!$B$10*Параметры!$B$11 -> 12500 | L8: =IF(I8="Годовая",Параметры!$B$5*H8*Параметры!$B$6/Параметры!$B$9,Параметры!$B$5*H8) -> 36113.014 | M8: =Параметры!$B$5*B8*D8*E8*S8/12 -> 5547.9452 | N8: =Параметры!$B$5*F8*Параметры!$B$6/Параметры!$B$9+G8 -> 6801.3699 | O8: =J8+K8-L8-M8-N8 -> -4351.3814 | P8: =O8-MAX(0,O8*Параметры!$B$15) -> -4351.3814 | Q8: =P8/Параметры!$B$5 -> -0.0087027628 | R8: =IF(OR(S8=0,Параметры!$B$5*B8*D8=0),0,12*RATE(S8,-(Параметры!$B$5*B8*D8+L8+M8+N8-K8)/S8,Параметры!$B$5*B8*D8,0)) -> 0.31791112 | S8: 4.9315068
A9: Оптимистичный пример | B9: 1 | C9: 0.36 | D9: 0.95 | E9: 0.015 | F9: 0.01 | G9: 2000 | H9: 0.1425 | I9: Годовая | J9: =IF(S9=0,0,-PMT(C9/12,S9,Параметры!$B$5*B9*D9)*S9-Параметры!$B$5*B9*D9) -> 51723.313 | K9: =Параметры!$B$5*Параметры!$B$10*Параметры!$B$11 -> 12500 | L9: =IF(I9="Годовая",Параметры!$B$5*H9*Параметры!$B$6/Параметры!$B$9,Параметры!$B$5*H9) -> 36113.014 | M9: =Параметры!$B$5*B9*D9*E9*S9/12 -> 3611.3014 | N9: =Параметры!$B$5*F9*Параметры!$B$6/Параметры!$B$9+G9 -> 4534.2466 | O9: =J9+K9-L9-M9-N9 -> 19964.751 | P9: =O9-MAX(0,O9*Параметры!$B$15) -> 19964.751 | Q9: =P9/Параметры!$B$5 -> 0.039929503 | R9: =IF(OR(S9=0,Параметры!$B$5*B9*D9=0),0,12*RATE(S9,-(Параметры!$B$5*B9*D9+L9+M9+N9-K9)/S9,Параметры!$B$5*B9*D9,0)) -> 0.22309423 | S9: 6.0821918
